lapa_file_store_helper/__init__.py
lapa_file_store_helper/main.py
lapa_file_store_helper-0.0.5.dist-info/METADATA
lapa_file_store_helper-0.0.5.dist-info/WHEEL
lapa_file_store_helper-0.0.5.dist-info/top_level.txt
lapa_file_store_helper-0.0.5.dist-info/RECORD
