Metadata-Version: 2.1
Name: lapa-file-store-helper
Version: 0.0.5
Summary: helper to access the file store layer for my personal server.
Home-page: https://github.com/thepmsquare/lapa_file_store_helper
Author: thePmSquare, Lav Sharma, Amish Palkar
Author-email: thepmsquare@gmail.com, lavsharma2016@gmail.com, amishpalkar302001@gmail.com
License: UNKNOWN
Platform: UNKNOWN
Classifier: Development Status :: 3 - Alpha
Classifier: Intended Audience :: Developers
Classifier: License :: OSI Approved :: MIT License
Classifier: Programming Language :: Python :: 3
Classifier: Programming Language :: Python :: 3.9
Requires-Dist: requests >=2.31.0
Requires-Dist: kiss-headers >=2.4.3
